machc/commercetools/__init__.py
machc/commercetools/user_adapter.py
machc_commercetools-0.0.2.dist-info/METADATA
machc_commercetools-0.0.2.dist-info/WHEEL
machc_commercetools-0.0.2.dist-info/top_level.txt
machc_commercetools-0.0.2.dist-info/RECORD
