Metadata-Version: 2.4
Name: machc.commercetools
Version: 0.0.2
Summary: Facilitates seamless integration of Machc components with the Commercetools platform.
Author-email: Viktor Tovstyi <viktor.tovstyi@gmail.com>
Requires-Python: >=3.12.3
Requires-Dist: utils==1.0.2
Requires-Dist: commercetools==2023.6.29
Requires-Dist: marshmallow==3.26.1
